.editorconfig
CHANGELOG.md
CONTRIBUTING.md
LICENSE
MANIFEST.in
Makefile
README.md
mkdocs.yml
requirements-docs.txt
requirements.txt
setup.cfg
setup.py
tox.ini
docs/changelog.md
docs/contributing.md
docs/index.md
docs/reference.md
src/dotenv/__init__.py
src/dotenv/__main__.py
src/dotenv/cli.py
src/dotenv/ipython.py
src/dotenv/main.py
src/dotenv/parser.py
src/dotenv/py.typed
src/dotenv/variables.py
src/dotenv/version.py
src/ginja_dotenv.egg-info/PKG-INFO
src/ginja_dotenv.egg-info/SOURCES.txt
src/ginja_dotenv.egg-info/dependency_links.txt
src/ginja_dotenv.egg-info/entry_points.txt
src/ginja_dotenv.egg-info/requires.txt
src/ginja_dotenv.egg-info/top_level.txt
tests/__init__.py
tests/conftest.py
tests/test_cli.py
tests/test_ipython.py
tests/test_main.py
tests/test_parser.py
tests/test_utils.py
tests/test_variables.py